progress_printer/__init__.py
progress_printer/progress_printer.py
progress_printer-0.7.dist-info/LICENSE
progress_printer-0.7.dist-info/METADATA
progress_printer-0.7.dist-info/WHEEL
progress_printer-0.7.dist-info/top_level.txt
progress_printer-0.7.dist-info/RECORD
