Metadata-Version: 2.1
Name: progress-printer
Version: 0.7
Summary: Provides a progress indicator
Home-page: https://github.com/c-type/project_printer
Author: ctype
Author-email: ctypecodes@gmail.com
License: MIT
Platform: UNKNOWN
Requires-Dist: numpy
Requires-Dist: datetime
